ipython_memory_usage/__init__.py
ipython_memory_usage/ipython_memory_usage.py
ipython_memory_usage/ipython_memory_usage_perf.py
ipython_memory_usage/perf_process.py
ipython_memory_usage-1.8.3.dist-info/LICENSE.txt
ipython_memory_usage-1.8.3.dist-info/METADATA
ipython_memory_usage-1.8.3.dist-info/WHEEL
ipython_memory_usage-1.8.3.dist-info/top_level.txt
ipython_memory_usage-1.8.3.dist-info/RECORD
