Metadata-Version: 2.1
Name: ipython-memory-usage
Version: 1.8.3
Summary: A Jupyter/IPYthon cell based memory and CPU profiler
Author-email: Ian Ozsvald <ian@ianozsvald.com>
License: 
Project-URL: Homepage, https://github.com/ianozsvald/ipython_memory_usage
Project-URL: Issues, https://github.com/ianozsvald/ipython_memory_usage
Classifier: Programming Language :: Python :: 3
Classifier: License :: OSI Approved :: MIT License
Classifier: Operating System :: OS Independent
Requires-Python: >=3.7
License-File: LICENSE.txt
Requires-Dist: IPython >=7.0
Requires-Dist: memory-profiler
Requires-Dist: psutil
